MIGNON/Data_Aug.py
MIGNON/Functions.py
MIGNON/Transformations.py
MIGNON/__init__.py
MIGNON-1.0.1.dist-info/LICENSE.txt
MIGNON-1.0.1.dist-info/METADATA
MIGNON-1.0.1.dist-info/WHEEL
MIGNON-1.0.1.dist-info/top_level.txt
MIGNON-1.0.1.dist-info/RECORD
