Metadata-Version: 2.1
Name: MIGNON
Version: 1.0.1
Summary: MIGNON (Multiplexed Imaging auGmeNtatiONs) is a tool to generate data augmentations of multiplexed images. Given an IMC array and a mask array, augmentations can be generated. Possible augmentations that can be selected are Shift, Rotate, Merge, Expand, and Shrink. Users can select the probability to apply each augmentation and the desired number of augmentations to generate. The output includes original cell expressions and augmented cell expressions.
Home-page: https://github.com/camlab-bioml/MIGNON
Author: Kevin Sun, Jett Lee, Kieran Campbell
Author-email: kierancampbell@lunenfeld.ca
License: gpl-2.0
Keywords: Data Augmentation,Multiplexed Imaging
Classifier: Programming Language :: Python :: 3
Classifier: License :: OSI Approved :: GNU General Public License v2 (GPLv2)
Classifier: Operating System :: OS Independent
Classifier: Topic :: Scientific/Engineering :: Bio-Informatics
License-File: LICENSE.txt
Requires-Dist: numpy
Requires-Dist: scikit-image
Requires-Dist: scipy
Requires-Dist: anndata
